setup.cfg
setup.py
bin/swiftly
swiftly/__init__.py
swiftly/cli.py
swiftly/client.py
swiftly/concurrency.py
swiftly.egg-info/PKG-INFO
swiftly.egg-info/SOURCES.txt
swiftly.egg-info/dependency_links.txt
swiftly.egg-info/top_level.txt