Metadata-Version: 1.0
Name: swiftly
Version: 1.9
Summary: Client for Swift
Home-page: http://gholt.github.com/swiftly/
Author: Gregory Holt
Author-email: swiftly@brim.net
License: UNKNOWN
Platform: UNKNOWN
